docs/_hooks/shortcodes.py
examples/cms-batch/config
examples/cms-batch/gen.py
examples/cms-batch/judge.py
examples/cms-batch/sample.in
examples/cms-batch/sample.out
examples/cms-batch/solve_all_ones.java
examples/cms-batch/solve_last_big.cpp
examples/cms-batch/solve_small_k.py
examples/cms-batch/statement.md
examples/cms-batch/validate.py
examples/cms-batch/solve_spread/Cargo.lock
examples/cms-batch/solve_spread/Cargo.toml
examples/cms-batch/solve_spread/src/main.rs
examples/opendata/config
examples/opendata/gen.py
examples/opendata/judge.py
examples/opendata/sample.in
examples/opendata/sample.out
examples/opendata/solve_all_ones.java
examples/opendata/solve_last_big.cpp
examples/opendata/solve_small_k.py
examples/opendata/statement.md
examples/opendata/validate.py
examples/opendata/solve_spread/Cargo.lock
examples/opendata/solve_spread/Cargo.toml
examples/opendata/solve_spread/src/main.rs
examples/organization-configs/README.md
examples/organization-configs/cms-base-v1
examples/organization-configs/cms-batch-v1
examples/organization-configs/cms-communication-v1
examples/organization-configs/opendata-v1
fixtures/max/solve_env.py
fixtures/max/solve_judge.py
fixtures/max/validate.py
fixtures/max/solve_py/lib.py
fixtures/max/solve_py/solve.py
fixtures/max/solve_py_cpp/run.py
fixtures/odd_stub/gen.py
fixtures/sum_cms/gen.py
fixtures/sum_cms/gen_dummy.py
fixtures/sum_cms/gen_incomplete.py
fixtures/sum_cms/gen_no_lf.py
fixtures/sum_cms/gen_same_out.py
fixtures/sum_cms/solve.py
fixtures/sum_cms/solve_0b.py
fixtures/sum_cms/solve_no_lf.py
fixtures/sum_cms/validate.py
fixtures/sum_cms/validate_strict.py
fixtures/sum_kasiopea/gen_2.py
fixtures/sum_kasiopea/judge_py.py
fixtures/sum_kasiopea/solve.py
fixtures/sum_kasiopea/solve_0b.py
fixtures/sum_kasiopea/validate.py
fixtures/sum_kasiopea/validate_strict.py
pisek/__init__.py
pisek/__main__.py
pisek/init.py
pisek/user_errors.py
pisek/version.py
pisek/visualize.py
pisek/cms/__init__.py
pisek/cms/dataset.py
pisek/cms/result.py
pisek-2.2.2.dist-info/licenses/LICENSE
pisek-2.2.2.dist-info/METADATA
pisek-2.2.2.dist-info/WHEEL
pisek-2.2.2.dist-info/entry_points.txt
pisek-2.2.2.dist-info/top_level.txt
pisek-2.2.2.dist-info/RECORD
