Metadata-Version: 2.4
Name: pisek
Version: 2.2.2
Summary: Tool for developing tasks for programming competitions.
Author-email: Václav Volhejn <vaclav.volhejn@gmail.com>, Jiří Beneš <mail@jiribenes.com>, Michal Töpfer <michal.topfer@gmail.com>, Jiri Kalvoda <jirikalvoda@kam.mff.cuni.cz>, Daniel Skýpala <skipy@kam.mff.cuni.cz>, Benjamin Swart <benjaminswart@email.cz>, Antonín Maloň <git@tonyl.eu>
Maintainer-email: Daniel Skýpala <skipy@kam.mff.cuni.cz>
License-Expression: GPL-3.0-or-later
Project-URL: Homepage, https://piskoviste.github.io/pisek/
Project-URL: Issues, https://github.com/piskoviste/pisek/issues
Classifier: Programming Language :: Python :: 3
Classifier: Operating System :: POSIX :: Linux
Requires-Python: >=3.11
License-File: LICENSE
Requires-Dist: argcomplete
Requires-Dist: colorama
Requires-Dist: pydantic
Requires-Dist: readchar
Provides-Extra: dev
Requires-Dist: black; extra == "dev"
Requires-Dist: commitizen; extra == "dev"
Requires-Dist: mypy; extra == "dev"
Dynamic: license-file
